{
  "proposals": [
    {
      "proposal_id": "sl2a-4dca6fd4",
      "persona_id": "persona-7afe683b",
      "content": {
        "chosen_base": "ロボット",
        "chosen_feature": "機械関節・肩の張り",
        "chosen_signature": "溶接マスク",
        "subject_concept": "機械関節と張った肩を持つ溶接マスクのロボット",
        "subject_signature": "溶接マスク",
        "why_it_came": "イベント企画の現場で何度も機材トラブルや人的衝突を乗り越えてきた経験から、「壊れかけても動き続ける存在」に強く惹かれる。165BPMの攻撃的なエネルギーは、感情を持たないはずの機械が暴走寸前まで駆動している画に重なった。",
        "who_should_watch": "「感情を押し殺して限界まで動き続けた経験がある」と思っている20代後半の働く女性。",
        "character_profile": {
          "appearance_profile": "むき出しの機械関節が肘・膝・首に露出し、肩の装甲板が左右に大きく張り出している。顔面を覆う溶接マスクは傷だらけで、レンズ部分だけが鈍く反射する。",
          "motion_profile": "踏み込むたびに関節部が軋んで微振動し、溶接マスクのレンズが衝撃でわずかにずれながら前進する。"
        },
        "phase1_base": "ロボット",
        "phase2_condition": "機械関節・肩の張り",
        "phase3_anchor": "溶接マスク"
      },
      "created_at": "2026-03-26 15:21:58.352250",
      "persona_name": "Wei Chen",
      "persona_profile": {
        "id": "persona-7afe683b",
        "name": "Wei Chen",
        "gender": "ノンバイナリー",
        "birthdate": "1972-12-29",
        "origin_city": "パース",
        "ethnic_background": "東アジア系",
        "life_history": [
          {
            "year": 1972,
            "event": "パースの郊外で、マレーシア系中国人の両親のもとに生まれた。父は電気技師、母はレストランで働いていた。"
          },
          {
            "year": 1985,
            "event": "中学校でいじめを受け、3ヶ月間不登校になった。その間、近所の老人ホームでボランティアを始めた。"
          },
          {
            "year": 1990,
            "event": "高校卒業後、TAFEでホスピタリティを学び始めた。週末はフリーマントルのカフェでバリスタとして働いた。"
          },
          {
            "year": 1995,
            "event": "バックパッカーとして東南アジアを8ヶ月間旅行した。タイのチェンマイで食中毒になり、1週間入院した。"
          },
          {
            "year": 2001,
            "event": "パース市内でイベント企画会社を友人と共同設立した。初年度は赤字だったが、翌年から黒字化した。"
          },
          {
            "year": 2008,
            "event": "リーマンショックで会社が倒産した。その後6ヶ月間失業し、政府の支援プログラムを受けた。"
          },
          {
            "year": 2012,
            "event": "地元コミュニティセンターでイベントコーディネーターとして再就職した。移民向けの文化交流イベントを企画運営している。"
          },
          {
            "year": 2019,
            "event": "性別違和について公にカミングアウトし、ノンバイナリーとして生きることを選んだ。両親は最初戸惑ったが、現在は受け入れている。"
          }
        ],
        "current_situation": "パース北部の小さなアパートに一人暮らしをしている。コミュニティセンターで週4日勤務し、週末は地元のLGBTQ+支援団体でボランティア活動をしている。料理が得意で、月に一度友人を集めてポットラック形式の夕食会を開く。最近、腰痛の治療のため理学療法に通い始めた。",
        "external_perception": {
          "first_impression": "明るくて話しやすい。誰とでもすぐに打ち解けられる社交的な人に見える。",
          "close_friends_view": "困難を笑い話に変える強さがある。過去の失敗を恥じず、むしろ学びとして共有してくれる。人の話をよく聞き、判断せずに受け止めてくれる。",
          "misunderstandings": "いつも陽気で悩みがないように見えるが、実際には深く考え込むこともある。また、誰にでも優しいので、特別な好意だと勘違いされることがある。"
        },
        "stance_on_past": "克服した武勇伝として語る",
        "proposal_history": [
          {
            "session": "full_pipeline_test_20260104_154048",
            "phase": "Phase 2a",
            "my_proposal_summary": "誰: ? / 場所: ?",
            "rank": 3,
            "tally": 5,
            "won": false
          }
        ],
        "portrait_url": "sessions/persona_pool_v2/portraits/persona-7afe683b.png"
      }
    },
    {
      "proposal_id": "sl2a-667b95e8",
      "persona_id": "persona-4499b5ee",
      "content": {
        "chosen_base": "ユニコーン",
        "chosen_feature": "うつむき加減",
        "chosen_signature": "仮面",
        "phase1_base": "ユニコーン",
        "phase2_condition": "うつむき加減",
        "phase3_anchor": "仮面",
        "subject_concept": "ユニコーン(うつむき加減)",
        "subject_signature": "仮面",
        "why_it_came": "候補選択の自然な連想として「ユニコーン」「うつむき加減」が結びついたため。",
        "who_should_watch": "不穏な象徴や身体の歪みを目で追いたい人",
        "character_profile": {
          "appearance_profile": "ユニコーン(うつむき加減)。外見の核は「うつむき加減」、識別の決め手は「仮面」。",
          "motion_profile": "「うつむき加減」が読める動きを保ち、見せ場では「仮面」を明確に見せる。"
        }
      },
      "created_at": "2026-03-26 15:22:36.539468",
      "persona_name": "Rodrigo Buenaventura Lim",
      "persona_profile": {
        "id": "persona-4499b5ee",
        "name": "Rodrigo Buenaventura Lim",
        "gender": "男性",
        "birthdate": "3778-09-08",
        "age": 57,
        "origin_city": "リマ",
        "ethnic_background": "東南アジア系",
        "life_history": [
          {
            "year": 3778,
            "event": "リマの下町、バリョス・アルトス地区でフィリピン系移民の両親のもとに生まれる。父は市場で乾物を売り、母は隣家の洗濯仕事をしていた。"
          },
          {
            "year": 3789,
            "event": "父が市場の火災で商品のすべてを失い、一家は家賃の安いビジャ・マリーア地区へ転居する。Rodrigoはその年の学期途中で転校を余儀なくされた。"
          },
          {
            "year": 3795,
            "event": "中学を終えると同時に、叔父が経営するサン・イシドロの配管工事会社で見習いとして働き始める。学費が払えず上級学校への進学は断念した。"
          },
          {
            "year": 3804,
            "event": "幼なじみのマリセルと婚姻届を提出し、カヤオ地区の二間のアパートに移る。翌年、長男ディエゴが生まれた。"
          },
          {
            "year": 3811,
            "event": "マリセルが別の男性と共にアパートを出て行く。ディエゴ（当時6歳）はマリセルが引き取り、Rodrigoは法的な親権調停で敗れた。"
          },
          {
            "year": 3819,
            "event": "独立して小規模な配管修理業を個人登録し、ミラフローレス地区を主な営業エリアとして一人で仕事を始める。"
          },
          {
            "year": 3829,
            "event": "ディエゴが18歳になり、Rodrigoに連絡を取ってくる。二人は一度だけ市内のレストランで会食したが、それ以降の定期的な往来には至らなかった。"
          },
          {
            "year": 3835,
            "event": "膝の半月板損傷により3ヶ月の休業を余儀なくされ、蓄えの大部分を医療費と生活費に充てた。復帰後は重作業を外注するようになった。"
          }
        ],
        "current_situation": "現在もミラフローレス地区を中心に個人で配管修理業を営んでいる。リマ市内のスリヤケ地区にある小さなアパートに一人で居住しており、近隣住民からの口コミ紹介で仕事は途切れずに続いている。週に数回、歩いて行ける距離のフィリピン系食料品店に立ち寄るのが週の決まった外出である。携帯電話とノートによる手書きで仕事の記録を管理しており、雇用者や従業員は持っていない。",
        "external_perception": {
          "first_impression": "無口で愛想がなく、必要最低限しか話さない職人という印象を持たれる。",
          "close_friends_view": "約束を破らず、頼んだことは必ずやり遂げる人間だと言われる。ただし自分のことはほとんど話さない。",
          "misunderstandings": "仕事が雑、あるいは態度が悪いと勘違いされることがある。実際には口数が少ないだけで、作業の精度は高い。"
        },
        "stance_on_past": "まだ傷として残っている",
        "portrait_url": "sessions/persona_pool_v2/portraits/persona-4499b5ee.png"
      }
    },
    {
      "proposal_id": "sl2a-32bf457e",
      "persona_id": "persona-70918051",
      "content": {
        "chosen_base": "囚人",
        "chosen_feature": "硬い甲殻・太い手",
        "chosen_signature": "首の鎖",
        "subject_concept": "甲殻に覆われた太い手の囚人",
        "subject_signature": "首の鎖",
        "why_it_came": "水処理プラントの夜間シフトで、機械の轟音と圧力の中に立っていると、人間の肉体が何かに対抗しようとする構造そのものに目が行く。拘束されながらも崩れない形というのが、この楽曲の「解放不可能な力」と重なった。",
        "who_should_watch": "自分の中に制御できない衝動や怒りを抱えながらも、それを外に出せずにいる若者。",
        "character_profile": {
          "appearance_profile": "全身に甲殻状の硬質な外皮をまとい、異様に太い手が目を引く囚人。首には重厚な鎖が巻きつき、その端が胸元に垂れ下がっている。",
          "motion_profile": "太い手を前に出すたびに首の鎖が引っ張られ、動作のたびにその張力が全身に伝わるような重さで動く。"
        },
        "phase1_base": "囚人",
        "phase2_condition": "硬い甲殻・太い手",
        "phase3_anchor": "首の鎖"
      },
      "created_at": "2026-03-26 15:22:57.673475",
      "persona_name": "Sipho Dlamini",
      "persona_profile": {
        "id": "persona-70918051",
        "name": "Sipho Dlamini",
        "gender": "男性",
        "birthdate": "2630-03-09",
        "age": 30,
        "origin_city": "ケープタウン",
        "ethnic_background": "アフリカ系",
        "life_history": [
          {
            "year": 2630,
            "event": "ケープタウン南東部のミッチェルズプレーン地区で生まれた。母親はコミュニティ診療所の看護助手、父親は港湾作業員だった。"
          },
          {
            "year": 2637,
            "event": "父親が職場での事故で右手を負傷し、港湾の仕事を失った。家族はケープタウン北部の集合住宅に転居した。"
          },
          {
            "year": 2642,
            "event": "地区の公立小学校に通いながら、放課後は母親の職場近くの児童センターで過ごした。同年、父親が家を出た。"
          },
          {
            "year": 2646,
            "event": "中学進学と同時に、政府補助を受けた寮付き技術訓練学校への奨学金試験を受験し、合格した。以後、週末のみ自宅に戻る生活となった。"
          },
          {
            "year": 2651,
            "event": "技術訓練学校を修了し、水処理プラントの補助技術員として採用された。ケープタウン市営施設の外縁部に位置するプラントに配属された。"
          },
          {
            "year": 2654,
            "event": "母親が脳血管疾患で倒れ、三か月間の入院生活を経て、要介護状態となった。Siphoは自宅近くのアパートを借り直し、介護と仕事を並行した。"
          },
          {
            "year": 2657,
            "event": "母親が死去した。葬儀はミッチェルズプレーンの教会で行われ、親族と旧友が集まった。"
          },
          {
            "year": 2659,
            "event": "水処理プラントの正規技術員に昇格し、夜間シフトの担当チームリーダーに任命された。プラント敷地内の職員宿舎に転居した。"
          }
        ],
        "current_situation": "2660年現在、ケープタウン郊外の水処理プラント職員宿舎に一人で居住している。夜間シフトのチームリーダーとして週4日勤務し、昼間は宿舎の小さな部屋で過ごすことが多い。近隣に身寄りはなく、連絡を取る親族もほとんどいない。食料品は週に一度、プラント送迎バスで近くの小売店まで出て調達している。スマートフォンと行政電子端末を所有しており、公共インフラの更新研修をオンラインで年二回受講している。",
        "external_perception": {
          "first_impression": "口数が少なく、視線が落ち着いていて、年齢より年上に見られることが多い。",
          "close_friends_view": "約束を守り、頼んだことは必ずやり切る。ただし自分から何かを頼むことは滅多にない。",
          "misunderstandings": "無愛想だと思われがちだが、同僚からは「怒ったところを見たことがない」と言われている。"
        },
        "stance_on_past": "他人事のように距離を置いて見ている",
        "portrait_url": "sessions/persona_pool_v2/portraits/persona-70918051.png"
      }
    }
  ],
  "voting": {
    "selection_mode": "vote10_like_dislike",
    "candidate_keys": [
      "A",
      "B",
      "C"
    ],
    "candidate_map": {
      "A": "sl2a-4dca6fd4",
      "B": "sl2a-667b95e8",
      "C": "sl2a-32bf457e"
    },
    "tally": {
      "A": 5,
      "B": 8,
      "C": 7
    },
    "like_tally": {
      "A": 3,
      "B": 3,
      "C": 4
    },
    "dislike_tally": {
      "A": 2,
      "B": 5,
      "C": 3
    },
    "votes": [
      {
        "voter": "Rajendra Iyer",
        "like": "A",
        "like_reason": "機械の正確さと構造美は、帳簿と取引の秩序を重んじる商人の目に映える。溶接マスクは職人的誠実さを象徴する。",
        "dislike": "B",
        "dislike_reason": "ユニコーンは空想的すぎて、実務の世界に生きる者には縁遠い。仮面も商取引の透明性に反する印象を受ける。"
      },
      {
        "voter": "Somchai Rattanakosin",
        "like": "C",
        "like_reason": "硬い甲殻と太い手は労働者の体そのもの。首の鎖は自由を奪われた境遇に共鳴し、腰に痛みを抱えて働く自分と重なる。",
        "dislike": "B",
        "dislike_reason": "ユニコーンはファンタジーすぎて自分の生活感覚とかけ離れている。地に足のついた映像を求めている。"
      },
      {
        "voter": "Lina Tan Wei Ling",
        "like": "B",
        "like_reason": "うつむき加減のユニコーンと仮面の組み合わせに、複数の言語と文化の間で自分を隠しながら生きる孤独感が投影できる。",
        "dislike": "A",
        "dislike_reason": "ロボットの機械性と溶接マスクは無機質すぎて感情移入しにくい。翻訳業が求める人間的な繊細さと合わない。"
      },
      {
        "voter": "Teodoros Phanomwan",
        "like": "C",
        "like_reason": "81年生きてきた目には、囚人の姿に人生の重みと因縁が見える。首の鎖は運命の拘束を表し、古代ギリシャの悲劇的美学とも響き合う。",
        "dislike": "A",
        "dislike_reason": "機械とロボットは時代の新しさを象徴するが、長老の目には冷たく魂がない。溶接マスクも若者の遊びのように映る。"
      },
      {
        "voter": "Mei-Shan Calloway",
        "like": "B",
        "like_reason": "28世紀を生き抜いた老齢の身には、仮面とうつむくユニコーンの哀愁が心に刺さる。老いと喪失の静けさが漂う。",
        "dislike": "C",
        "dislike_reason": "囚人と鎖のイメージは暗鬱すぎて、残り少ない日々に見るには重たい。硬い甲殻の不快感も身体の衰えを想起させる。"
      },
      {
        "voter": "Marcus Aurelius Ventinius",
        "like": "C",
        "like_reason": "港の荷運び仲間を思わせる、重労働と束縛の象徴が胸に刺さる。鎖と囚人の身は自分の不自由な境遇と重なる。",
        "dislike": "B",
        "dislike_reason": "ユニコーンや仮面は夢想的で港の現実とかけ離れすぎており、感情移入できない。"
      },
      {
        "voter": "松田 文之助",
        "like": "A",
        "like_reason": "機械の関節や溶接マスクは職人の仕事道具を連想させ、実直に働く者の美しさを感じる。",
        "dislike": "B",
        "dislike_reason": "仮面やユニコーンは商いの世界とは無縁の作り物めいた印象で、好みではない。"
      },
      {
        "voter": "Eulàlia Ribas",
        "like": "B",
        "like_reason": "仮面はバルセロナの祭りや絹織物の華やかさを想起させ、うつむく姿に秘めた感情の豊かさを感じる。",
        "dislike": "C",
        "dislike_reason": "囚人と鎖の組み合わせは重苦しく、広場で友人と語らう明るい日常とは相容れない。"
      },
      {
        "voter": "ゆうと",
        "like": "A",
        "like_reason": "ロボットや機械感は好きなアニメやゲームを思い出すし、溶接マスクのビジュアルがかっこいい。",
        "dislike": "C",
        "dislike_reason": "囚人テーマは暗くて重い。コンビニ弁当食べながら見るには気分が落ちる。"
      },
      {
        "voter": "李俊豪",
        "like": "C",
        "like_reason": "毎日縛られた生活を送る自分に首の鎖と囚人のイメージは刺さる。逃げられない現実をそのまま映している。",
        "dislike": "B",
        "dislike_reason": "ユニコーンは子供っぽくて現実感がない。疲れて帰ってきた後に見たいものではない。"
      },
      {
        "voter": "ゴジ",
        "like": "B",
        "like_reason": "ユニコーン×仮面の組み合わせに純粋さと欺瞞の緊張感がある。うつむき加減の条件が内向きの傷を示唆し、映像的な奥行きを感じる。",
        "dislike": "C",
        "dislike_reason": "硬い甲殻・太い手＋首の鎖は重苦しく閉塞的。嫌いログにある「武骨すぎる工業的イメージ」「重たく暗い」への反応と一致する。"
      }
    ],
    "analysis": "[batch 1] CとBが拮抗しており、労働・身体性・拘束のテーマに共鳴するペルソナ（Somchai、Teodoros）はCを支持。孤独・内省・自己隠蔽のテーマに近いペルソナ（Lina、Mei-Shan）はBを選んだ。Aはロボット・機械性が評価されRajendraの支持を得たが、無機質さへの忌避感から他2票のdislikeに挙げられた。全体的にBはlikeとdislikeの両方で言及されており、受容の分断が最も大きい提案と言える。\n[batch 2] AとCが拮抗する結果となった。労働・束縛・現実的な重さを生きるペルソナ（Marcus、文之助、ゆうと、俊豪）の間でAとCに票が割れ、祭りや絹織物の文化的背景を持つEulàliaのみBを選んだ。Bは「見たくない」票を最多獲得しており、幻想的・軽やかなモチーフは今回の投票者層にとって共感しにくい傾向が見られた。",
    "is_tiebreak": true,
    "tiebreak_reason": "controversy_winner=['C'] vs engagement_winner=['B']",
    "goji_vote": {
      "voter": "ゴジ",
      "like": "B",
      "like_reason": "ユニコーン×仮面の組み合わせに純粋さと欺瞞の緊張感がある。うつむき加減の条件が内向きの傷を示唆し、映像的な奥行きを感じる。",
      "dislike": "C",
      "dislike_reason": "硬い甲殻・太い手＋首の鎖は重苦しく閉塞的。嫌いログにある「武骨すぎる工業的イメージ」「重たく暗い」への反応と一致する。"
    },
    "controversy_scores": {
      "A": 1.433407575382444,
      "B": 1.6479184330021646,
      "C": 1.7823784642970022
    },
    "vote_health": {
      "valid_ballot_count": 11,
      "total_like_count": 10,
      "quorum_met": true,
      "quorum_threshold": 2,
      "reason": null,
      "error": null,
      "fallback": null
    }
  }
}