{
  "session_id": "session-20260226-212505-f8cc",
  "exported_from": "state_snapshot",
  "phase1": {
    "proposals": [
      {
        "proposal_id": "prop-78b4114d",
        "persona_id": "persona-dfc6a221",
        "content": {
          "creative_seed": "persona-dfc6a221:9c350636",
          "self_analysis": "私は物事をすぐに言語化しない。見ていて、溜めて、ずっと後になってから意味に気づくタイプ。感情を表に出すことへの不信感がある——表に出た感情は既に加工されているから。本物は静かで、汚くて、誰にも見せたくないものだと思っている。ユーモアは乾いていて、笑わせようとしない。回復力は派手さゼロ——ただ次の日も動いているだけ。",
          "what_i_saw": "夜中、誰も起きていない時間帯。ベッドの上で横向きに寝ながら、暗い天井にスマホの画面を向けて自撮りしている少年。録画ボタンを押したまま、何も言わない。ただ目だけが動いている。画面の隅に赤い録画マークが点滅している。",
          "why_it_came": "歌詞に「誰にも見せないそれだけが本物」という行がある。私がそこで止まったのは、本物であることの条件が『見せないこと』だと言っているからだ。MVが普通やること——見せること、伝えること、共有すること——と真逆の宣言。だとすれば、このMVで最も緊張が走る瞬間は、見せるはずのない録画が映っている瞬間、つまり本物が漏れ出している瞬間だと思った。暗さではなく、漏れること自体の静かな高揚。[起点=lyrics][解釈=漏れ・本物・不可視][トーン=counterpoint]",
          "theme": "「見せないこと」が本物の証だった少年が、気づかないうちに誰かに見られている",
          "hook_scene": {
            "focus": "15歳前後の少年——制服のシャツのボタンが一つだけ外れている",
            "place": "夜中の自室、電気は消えていて唯一の光源はスマホの画面だけ",
            "action": "横向きに寝たまま、スマホを天井に向けて録画中——しかし何も話さず、ただ目だけが画面の外を追っている",
            "detail": "画面の右上隅で赤い録画インジケーターが点滅している。少年はそれを見ていない",
            "question": "彼は何を撮っているのか——それとも録画していることを忘れているのか",
            "when": "chorus1終わり直前（79秒付近）、「壊れた僕の方が美しい」の余韻が消えた直後の無音に近い数秒"
          }
        },
        "created_at": "2026-02-26 12:26:03.206556"
      },
      {
        "proposal_id": "prop-4f069a44",
        "persona_id": "persona-85fe95b7",
        "content": {
          "creative_seed": "persona-85fe95b7:437add1e",
          "self_analysis": "私は長年、自分の感情を表に出さずに生きてきた人間だ。怒りも喜びも、内側に圧縮したまま機能し続ける。だから「爆発の寸前」よりも「爆発した後の静けさ」に目がいく。ユーモアは乾いていて、皮肉ではなく諦観に近い。回復力は劇的ではなく、翌朝も同じ時間に起きて同じパンを食べることで保たれている。この曲の14歳の怒りを聞いて、私が感じるのは共感ではなく——かすかな羨望だ。あれだけ沸騰できたこと自体が、一種の才能だった、という感覚。",
          "what_i_saw": "学校の廊下のロッカーが一列に並んでいる。授業中で廊下は無人。ロッカーの一つだけ、扉が半分開いたままになっている。その中から、ぐしゃぐしゃに丸められた紙が一枚、床に落ちかけている。カメラはその紙に近づいていく——ゆっくり、ゆっくり。紙が開くかどうかわからないまま、ベースラインが上がってくる。",
          "why_it_came": "この曲の緊張→解放の構造で、私が引っかかったのはサビの「解放」ではなく、その直前の「誰も知らない」という閉じた状態だった。廊下のロッカー、落ちかけた紙——これは「見られそうで見られていない」ギリギリの状態の映像だ。私は自分の感情を長く押し込めてきたせいか、爆発より「漏れ出す寸前」の物理的状態に美しさを感じる。紙が床に落ちる瞬間、それだけが「解放」だ——本人がいない場所で。[起点=lyrics][解釈=漏れ出し/無人の証拠/代理爆発][トーン=counterpoint]",
          "theme": "本人が去った後の空間だけが、本当のことを知っている",
          "hook_scene": {
            "focus": "一枚のぐしゃぐしゃに丸められたプリント用紙——進路希望調査票と読める、書かれた文字は見えない",
            "place": "平日の午前中、授業中の無人の廊下——スチール製ロッカーが両側に続き、蛍光灯だけが白く光っている",
            "action": "ロッカーの半開きの扉から紙がゆっくり落下しつつある——完全には落ちていない、途中で止まっている",
            "detail": "紙の角だけが蛍光灯の光を反射してわずかに白く光っており、床との距離は10センチ以下",
            "question": "誰がこれを丸めたのか——そして、なぜロッカーを閉め忘れて去ったのか",
            "when": "chorus1入り直前（48秒）——ドラムが鳴る0.5秒前にカメラが紙に最接近する"
          }
        },
        "created_at": "2026-02-26 13:31:47.777284"
      },
      {
        "proposal_id": "prop-da9604cc",
        "persona_id": "persona-734ac207",
        "content": {
          "creative_seed": "persona-734ac207:063c2956",
          "self_analysis": "長年の実務で感情を内側に押し込む癖がついた。でも押し込んだだけで消えてはいない。笑い話にできるようになった過去は、軽くしか見えない場所に本音が置いてある構造と似ている。14歳の荒れ方を見て「あー懐かしい種類の怒りだ」と思える距離感がある。暗さに感情移入するより、「その子はたぶん大丈夫になる」側から見ている。それが今の私の位置。",
          "what_i_saw": "進路希望調査票のコピー用紙が何百枚も教室の天井から降ってくる。一枚一枚に「YouTuber」と書いてある。少年は机の上に仁王立ちして、両腕を広げて紙を受け止めようとしている。笑っているのか泣いているのか、顔が紙で半分隠れているから分からない。",
          "why_it_came": "歌詞の中で一番「軽くて重い」行が『YouTuberって書いたら笑われて』だった。笑われることを想像しながら書いた、あの一瞬の逡巡。そこにこの曲の本当の体温がある気がした。叫び声より、書こうとして止まった鉛筆の動きの方が長く残る。誇張すれば祝祭になる。紙吹雪的な演出に変換した瞬間、暗さより高揚感が来た。[起点=lyrics][解釈=逡巡の祝祭化][トーン=uplift]",
          "theme": "笑われると分かっていて書いた一語が、百倍になって降ってくる夜",
          "hook_scene": {
            "focus": "制服姿の少年——ネクタイが緩んで斜め、右手に鉛筆を握ったまま",
            "place": "昼間の教室、蛍光灯全灯・窓から真昼の光が入る——しかし他の生徒は誰もいない",
            "action": "机の上に仁王立ちして両腕を広げ、天井から降り注ぐ大量のコピー用紙を全身で受け止めようとしている——受け止めるというより、浴びている",
            "detail": "足元の床に積もった紙の一枚、カメラが寄ると『YouTuber』という文字が見える——鉛筆の手書きで、書き直した跡がある",
            "question": "他の生徒がいない昼間の教室で、この紙はどこから来ているのか——そして少年の顔は、半分隠れていて笑っているのか泣いているのか判定できない",
            "when": "サビ頭「透明な檻の中で踊る人形」の直前——前奏が終わって一瞬無音になる瞬間にカットイン"
          }
        },
        "created_at": "2026-02-26 13:55:13.237640"
      }
    ],
    "voting": {
      "selection_mode": "vote10_like_dislike",
      "candidate_keys": [
        "A"
      ],
      "candidate_map": {
        "A": "prop-4f069a44"
      },
      "tally": {
        "A": 0
      },
      "like_tally": {
        "A": 0
      },
      "dislike_tally": {
        "A": 0
      },
      "votes": [],
      "analysis": "single_candidate",
      "is_tiebreak": false,
      "tiebreak_reason": null,
      "goji_vote": null
    }
  },
  "phase2a": {
    "proposals": [
      {
        "proposal_id": "sl2a-83a3f0b2",
        "persona_id": "persona-5caf3621",
        "content": {
          "phase1_base": "甲冑兵",
          "phase2_condition": "箱型胴体・機械関節",
          "phase3_anchor": "足枷",
          "subject_concept": "箱型胴体と機械関節を持つ甲冑兵",
          "subject_signature": "足枷",
          "character_profile": {
            "appearance_profile": "胸部から腰にかけて直方体に近い箱型の胴体を持ち、肘・膝・肩の各関節部に露出した金属の可動機構が組み込まれている。両足首には重量のある足枷が装着されており、左右対称に鎖の切れ端が残っている。",
            "motion_profile": "歩行のたびに足枷が床を引きずり、機械関節が連動して上半身の箱型フレームを上下に揺らす。"
          }
        },
        "created_at": "2026-02-26 13:55:23.209364"
      },
      {
        "proposal_id": "sl2a-6fc1ca85",
        "persona_id": "persona-54e12800",
        "content": {
          "phase1_base": "ハーピー",
          "phase2_condition": "六本腕・凹凸肌",
          "phase3_anchor": "口枷",
          "subject_concept": "六本腕の凹凸肌ハーピー",
          "subject_signature": "口枷",
          "character_profile": {
            "appearance_profile": "六本の腕が胴体から放射状に伸び、全身を覆う凹凸肌が光を不規則に拾う。金属製の口枷が顔の下半分を覆い、顎の動きを完全に封じている。",
            "motion_profile": "六本腕がそれぞれ異なるリズムで空を掻くたびに、口枷の金具が首元で小刻みに揺れる。"
          }
        },
        "created_at": "2026-02-26 13:55:40.216142"
      },
      {
        "proposal_id": "sl2a-369fb542",
        "persona_id": "persona-31f36291",
        "content": {
          "phase1_base": "からかさお化け",
          "phase2_condition": "二つの口・背ビレ",
          "phase3_anchor": "牙の首飾り",
          "subject_concept": "二つの口と背ビレを持つからかさお化け",
          "subject_signature": "牙の首飾り",
          "character_profile": {
            "appearance_profile": "傘の縁に沿って上下二列に並ぶ口と、柄の背面に突き出た連続する背ビレが体幹を縦断する。牙を繋いだ首飾りが傘の付け根に巻きつき、開閉のたびに揺れる。",
            "motion_profile": "傘を開く動作に連動して上の口と下の口が非同期にずれ、背ビレが扇状に広がる。"
          }
        },
        "created_at": "2026-02-26 13:55:56.852470"
      }
    ],
    "voting": {
      "selection_mode": "vote10_like_dislike",
      "candidate_keys": [
        "A",
        "B",
        "C"
      ],
      "candidate_map": {
        "A": "sl2a-83a3f0b2",
        "B": "sl2a-6fc1ca85",
        "C": "sl2a-369fb542"
      },
      "tally": {
        "A": 6,
        "B": 7,
        "C": 7
      },
      "like_tally": {
        "A": 3,
        "B": 3,
        "C": 4
      },
      "dislike_tally": {
        "A": 3,
        "B": 4,
        "C": 3
      },
      "votes": [
        {
          "voter": "ちづる",
          "like": "A",
          "like_reason": "甲冑兵という武士的なモチーフに日本的な親しみを感じる。箱型胴体の機械的な造形が看護の現場で見る義肢・器具を連想させ、人体と機械の境界への関心が湧く。",
          "dislike": "B",
          "dislike_reason": "六本腕・凹凸肌という身体的変形表現が、患者の身体に向き合う職業柄、生理的な不快感を呼び起こしやすい。"
        },
        {
          "voter": "ミン・チェン",
          "like": "C",
          "like_reason": "からかさお化けは中国でも傘の妖怪伝説と近いモチーフがあり文化的に馴染みやすい。二つの口と背ビレという非対称な造形がユニークで商業的な記憶に残りやすいと感じる。",
          "dislike": "A",
          "dislike_reason": "甲冑兵は平凡すぎてインパクトに欠ける。輸入代行で扱う商品のデザインを見慣れているため、既視感のある武士・騎士系モチーフには食指が動かない。"
        },
        {
          "voter": "おおたに けんじ",
          "like": "C",
          "like_reason": "南米の民芸品を長年扱ってきた目線で、牙の首飾りというアクセサリーモチーフに民族的な装飾美を感じる。からかさお化けの奇妙なユーモアも雑貨店主として好き。",
          "dislike": "B",
          "dislike_reason": "口枷という拘束具のモチーフが暗くて重苦しい。店のイメージに合わない暴力的な印象があり、純粋に「見たくない」と思った。"
        },
        {
          "voter": "Lakshmi Fernandes",
          "like": "B",
          "like_reason": "ハーピーは聖書や民間伝承でも馴染みのある霊的存在に近く、六本腕は神聖な多腕像（インド・ブラジル混交文化の影響）と重なって神秘的に映る。",
          "dislike": "C",
          "dislike_reason": "からかさお化けは東洋固有の文脈が強く、リオの市場で育った自分には何を表しているのかまったく伝わらない。牙の首飾りも呪術的で縁起が悪く感じる。"
        },
        {
          "voter": "Mei-Lin Kowalska",
          "like": "A",
          "like_reason": "甲冑兵は欧州の騎士文化と重なり、ベルリンで長年暮らしてきた身には最も絵になると思う。足枷という歴史的な拘束具も中世ヨーロッパの記憶を呼び起こし物語性がある。",
          "dislike": "C",
          "dislike_reason": "からかさお化けという概念自体が理解しにくく、二つの口・背ビレという造形も脈絡が見えない。孫たちに見せるにも説明に困りそうで敬遠したい。"
        },
        {
          "voter": "Graham Fletcher",
          "like": "A",
          "like_reason": "甲冑兵は息子が好きそうな戦士のイメージで分かりやすい。箱型胴体の機械感もカッコいい。",
          "dislike": "C",
          "dislike_reason": "からかさお化けは自分には馴染みがなく、何なのかよく分からない。牙の首飾りも不気味すぎる。"
        },
        {
          "voter": "Yolanda Chen Xiuying",
          "like": "B",
          "like_reason": "ハーピーは神話的で視覚的インパクトが強い。六本腕という独自性がユニークで印象に残る。",
          "dislike": "A",
          "dislike_reason": "甲冑兵は見慣れたモチーフで新鮮みがない。足枷というアンカーも重々しくて気が滅入る。"
        },
        {
          "voter": "Karim Haddad",
          "like": "C",
          "like_reason": "からかさお化けは日本の民俗的美学が面白い。二つの口と背ビレという組み合わせが建築的な複雑さを感じさせる。",
          "dislike": "B",
          "dislike_reason": "六本腕に凹凸肌と口枷の組み合わせがあまりに混沌としており、デザインとしてのまとまりを感じない。"
        },
        {
          "voter": "李秋蓮",
          "like": "C",
          "like_reason": "からかさお化けは自分が慣れ親しんだ世界の妖怪に近く、なじみ深い。牙の首飾りも護符のように見える。",
          "dislike": "B",
          "dislike_reason": "ハーピーは異国の化け物で不吉な印象がある。口枷という拘束具は見ていて心が痛む。"
        },
        {
          "voter": "Aminah binti Osman",
          "like": "B",
          "like_reason": "ハーピーは港で耳にした南洋や欧州の船乗りの話に出てくる翼ある怪物に似ており、異国情緒がある。",
          "dislike": "A",
          "dislike_reason": "甲冑兵は兵士を思わせ、争いや略奪を連想させる。足枷も奴隷の象徴のようで見たくない。"
        },
        {
          "voter": "ゴジ",
          "like": "C",
          "like_reason": "からかさお化けの二つの口と牙の首飾りは奇妙な愛嬌があって愛着が湧く",
          "dislike": "B",
          "dislike_reason": "六本腕に口枷という組み合わせが重くて息苦しい。凹凸肌も触感的に不快"
        }
      ],
      "analysis": "[batch 1] AとCが各2票のlikeを獲得し人気が拮抗した。Aは日本的・欧州的な武士／騎士イメージとして文化圏をまたいで共感を呼んだ一方、Cはからかさお化けのユーモアと牙の首飾りの民芸的装飾美が評価された。Bはハーピーの霊的・神秘的魅力でLakshmiから支持を得たが、口枷という拘束表現の暗さと身体的変形への生理的忌避からdislikeも2票を集め、最も好悪が分かれる候補となった。\n[batch 2] CとBが拮抗しており、Cは文化的親近感や意匠の独自性で東アジア・高齢ペルソナに支持された。Bはビジュアルインパクトと神話的スケール感で若年・国際志向のペルソナに選ばれた。Aは分かりやすさで子育て世代に支持された一方、既視感と足枷の重さが複数票のdislikeを集めた。",
      "is_tiebreak": true,
      "tiebreak_reason": null,
      "goji_vote": {
        "voter": "ゴジ",
        "like": "C",
        "like_reason": "からかさお化けの二つの口と牙の首飾りは奇妙な愛嬌があって愛着が湧く",
        "dislike": "B",
        "dislike_reason": "六本腕に口枷という組み合わせが重くて息苦しい。凹凸肌も触感的に不快"
      }
    }
  },
  "phase3": {
    "proposals": [
      {
        "proposal_id": "world-c61e76db",
        "persona_id": "persona-fb9ac898",
        "content": {
          "world_setting": {
            "premise": "重力が「層」によって異なる世界で、人々は浮遊岩と石段を繋いだ空中足場の上で暮らしている。地上は禁忌の泥地であり、誰も降りようとしない。",
            "rules": [
              "高度が上がるほど重力が弱くなり、最上層では人間が意図せず浮き始める",
              "浮遊岩は定期的に位置をずらすため、空中足場の地図は毎朝更新される",
              "発光苔が生えている岩は安全な重力層の目印とされている",
              "泥地に触れた者は「沈んだ人」と呼ばれ、社会的に存在しないものとして扱われる"
            ],
            "society": "層ごとに居住権があり、上層ほど地位が高い。層間の移動は城壁階段と木製クレーンで管理され、通行には印章が必要。最上層の者だけが「浮き人」と呼ばれ、法の外に置かれる。",
            "daily_life": "朝に足場の位置確認、昼に岩棚の市場で物々交換、夜は発光苔の明かりで眠る。移動は跳躍と滑車が基本で、走るという概念がない。",
            "values": "「軽さ」が美徳とされ、荷物を多く持つ者は蔑まれる。地上への郷愁を口にすることはタブー。発光苔を持ち帰ることは幸運の象徴とされている。",
            "visual_signifiers": [
              "空中に無数に連なる木製足場と浮遊岩、その隙間から見える泥地の暗さ",
              "発光苔が点々と光る岩肌と、そこだけ緑に染まる空気",
              "城壁階段を登る人影と、層を越えるたびに服の裾がゆっくり浮き上がる描写"
            ],
            "limits": "地上（泥地）への降下は物理的には可能だが、社会的な死を意味するため誰も試みない。最上層より上は重力がゼロになり、戻れなくなる「帰還不能域」として封鎖されている。",
            "freedom": "帰還不能域の上には、いかなるルールも権力も届かない。そこへ飛んだ者の記録は抹消されるが、語り継がれる伝説として民の想像力の中だけで自由に存在し続ける。"
          },
          "_phase3_keyword_debug": {
            "candidate_sets": [
              {
                "set_id": "A",
                "keywords": [
                  "石碑",
                  "祭壇",
                  "カーブミラー",
                  "吊り滑車",
                  "地下換気塔",
                  "ドッキング柱",
                  "自転車レーン",
                  "見張り塔",
                  "石門",
                  "光のガード",
                  "河原石",
                  "信号機",
                  "浮遊島",
                  "祠",
                  "係留杭",
                  "水路",
                  "横断帯",
                  "城門",
                  "電柱",
                  "木桶"
                ],
                "lead_era": "modern",
                "era_counts": {
                  "ancient": 4,
                  "modern": 6,
                  "early_modern": 2,
                  "future": 2,
                  "medieval": 2,
                  "primitive": 2,
                  "isekai": 2
                },
                "alignment_score": 2.1
              },
              {
                "set_id": "B",
                "keywords": [
                  "浮遊柵",
                  "空中浮遊台",
                  "路面標識",
                  "排水口",
                  "バス停柱",
                  "信号機",
                  "竹垣",
                  "浮上ホーム",
                  "岩棚",
                  "城壁階段",
                  "空中足場",
                  "荷車置き場",
                  "作業台",
                  "石段",
                  "木槍立て",
                  "浮遊足場",
                  "通信箱",
                  "浮遊岩",
                  "自転車レーン",
                  "石の導水管"
                ],
                "lead_era": "modern",
                "era_counts": {
                  "future": 4,
                  "modern": 6,
                  "early_modern": 2,
                  "primitive": 2,
                  "medieval": 2,
                  "isekai": 2,
                  "ancient": 2
                },
                "alignment_score": 1.575
              },
              {
                "set_id": "C",
                "keywords": [
                  "砦壁",
                  "郵便ポスト",
                  "光のガード",
                  "白線",
                  "発光苔",
                  "木柵",
                  "浮き樽",
                  "縁石",
                  "祠",
                  "通信箱",
                  "空中レール",
                  "皮の天幕",
                  "木製クレーン",
                  "自転車レーン",
                  "泥地",
                  "排水口",
                  "発光路面",
                  "ドッキング柱",
                  "浮彫壁",
                  "井戸"
                ],
                "lead_era": "modern",
                "era_counts": {
                  "medieval": 2,
                  "modern": 6,
                  "future": 4,
                  "isekai": 2,
                  "early_modern": 2,
                  "primitive": 2,
                  "ancient": 2
                },
                "alignment_score": 1.575
              }
            ],
            "selected_set_id": "B",
            "selected_lead_era": "modern",
            "selected_era_counts": {
              "future": 4,
              "modern": 6,
              "early_modern": 2,
              "primitive": 2,
              "medieval": 2,
              "isekai": 2,
              "ancient": 2
            },
            "selected_overlap": [
              "岩棚",
              "城壁階段",
              "空中足場",
              "石段",
              "浮遊岩"
            ],
            "persona_alignment_score": 1.575
          }
        },
        "created_at": "2026-02-26 13:57:13.698863"
      },
      {
        "proposal_id": "world-6967d173",
        "persona_id": "persona-c4dc6019",
        "content": {
          "world_setting": {
            "premise": "記憶は水路を流れる。人々は自分の過去を「引き出す」のではなく、街に張り巡らされた水路から「すくい取る」ことで初めて思い出せる。",
            "rules": [
              "記憶は個人の脳内に保存されず、街の水路網に溶けて循環している",
              "水路から記憶をすくうには石臼型の「読み器」が必要で、誰でも他人の記憶を拾える",
              "水路が干上がった区画では、その時代の記憶ごと消滅する",
              "発光段差は記憶の密度を示す地形サインであり、光が強い場所ほど古い感情が堆積している",
              "松明を水面に近づけると記憶が映像として揺らめくが、触れると永久に失われる"
            ],
            "society": "記憶を管理する「水番」が最上位権力を持つ。水路の流量を操作することで特定の時代の記憶を隠蔽・放流し、都市の集合的認識を支配している。貧困層は干上がりかけた末端水路でかろうじて記憶をすくって生きる。",
            "daily_life": "朝、人々は水路沿いに並び、昨日の自分をすくい取ることから一日を始める。行燈看板は水路の流量と記憶の種類（喜/哀/怒）を色で示す生活インフラ。木樽に記憶を封じて売買する闇市が路地ごとに立つ。",
            "values": "「自分だけの記憶を持つこと」は密かな憧れであり、同時に重大な禁忌とされる。記憶を私有しようとする者は水番に追われ、水路に突き落とされる。美意識の基準は「どれだけ多くの他者の記憶を通過したか」＝深みのある人間とされる。",
            "visual_signifiers": [
              "街中を縦横に走る浅い石造り水路と、そこに映る無数の残像",
              "発光段差——水路の段差が青白く光り、密度が上がるほど色が金色に変わる",
              "石臼型の読み器を抱えて水辺にしゃがむ人影",
              "行燈看板が感情の色（青/赤/黄）で明滅する路地"
            ],
            "limits": "完全に私有された記憶は存在できない。水路の外で記憶を保持し続けることは物理的に不可能で、眠るたびに記憶は水へと流れ出す。水路を破壊することは存在ごと消される。",
            "freedom": "水路に流れ出た記憶は誰のものでもなく、誰のものでもある。すくった瞬間だけ、それは完全にあなたのものになる——所有権も罰則も存在しない、その数秒間だけ。"
          },
          "_phase3_keyword_debug": {
            "candidate_sets": [
              {
                "set_id": "A",
                "keywords": [
                  "骨の杭",
                  "獣道",
                  "城門",
                  "祭壇",
                  "移動ホーム",
                  "石の囲い",
                  "桟橋",
                  "浮遊コンテナ",
                  "石器束",
                  "断片地形",
                  "皮の天幕",
                  "アーチ壁",
                  "光の格子",
                  "燧石山",
                  "ケーブル束",
                  "路面標識",
                  "ドッキング柱",
                  "船着き場",
                  "鉄灯籠",
                  "空中橋"
                ],
                "lead_era": "primitive",
                "era_counts": {
                  "primitive": 6,
                  "medieval": 2,
                  "ancient": 2,
                  "future": 4,
                  "early_modern": 2,
                  "isekai": 2,
                  "modern": 2
                },
                "alignment_score": 0.3
              },
              {
                "set_id": "B",
                "keywords": [
                  "つる植物",
                  "かがり火",
                  "浮彫壁",
                  "石柱",
                  "網",
                  "石像門",
                  "石畳",
                  "停止線",
                  "光の格子",
                  "浮遊岩",
                  "石碑",
                  "焚き火跡",
                  "行燈看板",
                  "木の骨組み",
                  "露岩",
                  "光の帯",
                  "倒木",
                  "矢狭間",
                  "浮き樽",
                  "通信箱"
                ],
                "lead_era": "primitive",
                "era_counts": {
                  "primitive": 6,
                  "medieval": 2,
                  "ancient": 4,
                  "isekai": 2,
                  "modern": 2,
                  "future": 2,
                  "early_modern": 2
                },
                "alignment_score": 0.225
              },
              {
                "set_id": "C",
                "keywords": [
                  "発光段差",
                  "電線",
                  "行燈看板",
                  "ガードレール",
                  "石臼",
                  "空中レール",
                  "水路",
                  "岩棚",
                  "木樽",
                  "旗布",
                  "浮遊灯",
                  "浮遊標識",
                  "断片地形",
                  "石板",
                  "通行ゲート",
                  "磁気レール",
                  "幻光標識",
                  "跳ね橋",
                  "格子戸",
                  "松明"
                ],
                "lead_era": "future",
                "era_counts": {
                  "future": 6,
                  "modern": 2,
                  "early_modern": 2,
                  "primitive": 2,
                  "ancient": 2,
                  "medieval": 4,
                  "isekai": 2
                },
                "alignment_score": 0.3
              }
            ],
            "selected_set_id": "C",
            "selected_lead_era": "future",
            "selected_era_counts": {
              "future": 6,
              "modern": 2,
              "early_modern": 2,
              "primitive": 2,
              "ancient": 2,
              "medieval": 4,
              "isekai": 2
            },
            "selected_overlap": [
              "発光段差",
              "行燈看板",
              "石臼",
              "水路",
              "木樽",
              "松明"
            ],
            "persona_alignment_score": 0.3
          }
        },
        "created_at": "2026-02-26 13:59:07.503846"
      },
      {
        "proposal_id": "world-54eb6fa0",
        "persona_id": "persona-07a239d7",
        "content": {
          "world_setting": {
            "premise": "この世界では、感情は「熱」として体外に放出され、街の炉の跡に蓄積される。人々は炉を焚べることで他者の感情を借り受け、自分のものとして生きることができる。",
            "rules": [
              "感情を使い切った人間は「冷者（ひえもの）」と呼ばれ、表情を失い、街道標の傍らに立ち尽くす",
              "炉の跡が古いほど蓄積された感情は濃く、街の中心部ほど炉が密集し権威を持つ",
              "オベリスクは感情の蒸発地点を示す標であり、近づくほど他者の感情が皮膚から滲み込んでくる",
              "自分の感情を一切放出しない者は「原者」として隔離されるが、同時に最も豊かな内面を持つとされる"
            ],
            "society": "炉の管理権を持つ「焔族（ほのおぞく）」が都市を支配する。感情の売買が経済の基盤であり、路面標識には現在の感情相場が刻まれている。変圧器のような装置が炉から感情エネルギーを変換・分配する。",
            "daily_life": "朝、人々は最寄りの炉の跡で今日分の感情を「受け取り」、井戸のように汲み上げて体に馴染ませてから仕事に出る。排水溝には使い終わった感情の残滓が流れており、子どもはそこで遊ぶ。",
            "values": "感情を多く消費することが豊かさの証とされ、無感動は貧しさの象徴。しかし密かに「冷者」に憧れる若者層が存在し、原者文化が地下で広がっている。",
            "visual_signifiers": [
              "街角の炉の跡——使い込まれた黒い石組みの炉が路傍に点在し、淡い熱気が陽炎のように立ち昇っている",
              "オベリスクの周囲だけ空気が歪んで見え、近づく人の顔が次々と別の表情に塗り替えられていく",
              "路面標識に感情相場の数値が刻まれており、数値が高い区画ほど道行く人の動作が大袈裟になる",
              "石壁に染み付いた感情の痕跡——赤や青の染みが歴史の地層のように壁面に重なっている"
            ],
            "limits": "自分の感情を完全に「所有」することは制度上認められていない。感情は必ず炉を経由して社会に還元する義務がある。",
            "freedom": "炉が存在しない廃区域では感情の貸借が発生しないため、そこに住む者は制度の外で自分だけの感情を持てる。"
          },
          "_phase3_keyword_debug": {
            "candidate_sets": [
              {
                "set_id": "A",
                "keywords": [
                  "行燈看板",
                  "横断帯",
                  "市場屋台",
                  "通行ゲート",
                  "空中庭",
                  "浅瀬",
                  "消火栓",
                  "薪積み",
                  "街道標",
                  "路面標識",
                  "炉の跡",
                  "リニア軌道",
                  "井戸",
                  "石壁",
                  "変圧器",
                  "オベリスク",
                  "排水溝",
                  "ルーン柱",
                  "水門",
                  "石段"
                ],
                "lead_era": "ancient",
                "era_counts": {
                  "early_modern": 2,
                  "modern": 4,
                  "medieval": 2,
                  "future": 2,
                  "isekai": 2,
                  "primitive": 2,
                  "ancient": 6
                },
                "alignment_score": 0.3
              },
              {
                "set_id": "B",
                "keywords": [
                  "空中レール",
                  "光壁",
                  "竹垣",
                  "炉の跡",
                  "水晶灯",
                  "柱頭飾り",
                  "透過床",
                  "井桁",
                  "浮遊標識",
                  "荷車置き場",
                  "消火栓",
                  "通行ゲート",
                  "水路",
                  "車止め",
                  "空中浮遊台",
                  "信号機",
                  "霧の門",
                  "荷揚げ滑車",
                  "監視カメラ",
                  "木桶"
                ],
                "lead_era": "future",
                "era_counts": {
                  "future": 6,
                  "early_modern": 2,
                  "primitive": 2,
                  "isekai": 2,
                  "ancient": 2,
                  "medieval": 2,
                  "modern": 4
                },
                "alignment_score": 0.225
              },
              {
                "set_id": "C",
                "keywords": [
                  "移動ホーム",
                  "木柵",
                  "獣道",
                  "魔導灯",
                  "発光苔",
                  "桟橋",
                  "浮上ホーム",
                  "光の格子",
                  "鍛造炉",
                  "封印石",
                  "点字ブロック",
                  "石壁",
                  "発光路面",
                  "横断帯",
                  "巨岩",
                  "結界柱",
                  "列柱",
                  "木製看板",
                  "ルーン柱",
                  "水晶灯"
                ],
                "lead_era": "isekai",
                "era_counts": {
                  "future": 4,
                  "medieval": 2,
                  "primitive": 2,
                  "isekai": 6,
                  "early_modern": 2,
                  "modern": 2,
                  "ancient": 2
                },
                "alignment_score": 0.3
              }
            ],
            "selected_set_id": "A",
            "selected_lead_era": "ancient",
            "selected_era_counts": {
              "early_modern": 2,
              "modern": 4,
              "medieval": 2,
              "future": 2,
              "isekai": 2,
              "primitive": 2,
              "ancient": 6
            },
            "selected_overlap": [
              "街道標",
              "路面標識",
              "炉の跡",
              "井戸",
              "石壁",
              "変圧器",
              "オベリスク",
              "排水溝"
            ],
            "persona_alignment_score": 0.3
          }
        },
        "created_at": "2026-02-26 14:00:22.519307"
      }
    ],
    "vote": {
      "winner_key": "B",
      "tally": {
        "A": 6,
        "B": 8,
        "C": 6
      },
      "like_tally": {
        "A": 3,
        "B": 5,
        "C": 2
      },
      "dislike_tally": {
        "A": 3,
        "B": 3,
        "C": 4
      },
      "votes": [
        {
          "voter": "ミン・チェン",
          "like": "B",
          "like_reason": "記憶が流通・管理される仕組みが、情報や商品の流通を扱う自分の仕事感覚と重なり、社会構造のリアリティを感じる。貧富の格差が記憶の「アクセス権」に直結する点も現代的で惹きつけられる。",
          "dislike": "C",
          "dislike_reason": "感情を商品として売買するという概念が感情移入しにくく、炉やオベリスクといった装置の説明が複雑すぎて映像として想像しにくい。"
        },
        {
          "voter": "Amara Okafor",
          "like": "C",
          "like_reason": "炉や変圧器など、エネルギーを変換・分配する仕組みが自分の修理業の感覚と親和性が高い。感情が熱として物理的に流れる世界観はメカニカルな美しさがある。",
          "dislike": "A",
          "dislike_reason": "重力の層という設定は面白いが、空中足場や浮遊岩の描写が幻想的すぎて、自分の日常感覚から遠く感情移入できない。"
        },
        {
          "voter": "Kofi Szabó",
          "like": "A",
          "like_reason": "浮遊する岩や空中の足場、重力が変わるたびに服が浮き上がる描写がゲームみたいでワクワクする。上に行くほど強くなるという冒険感がかっこいい。",
          "dislike": "B",
          "dislike_reason": "水路から記憶をすくうという話は難しくてよくわからないし、街の水路の映像があまり面白そうに思えない。"
        },
        {
          "voter": "Siriwan Andersen",
          "like": "B",
          "like_reason": "記憶が水のように流れ、すくい取るものだという詩的な発想に心が動いた。36年間毎日同じ時間に起き、夫の思い出と共に生きる自分には、記憶の在り方を問う世界が深く刺さる。",
          "dislike": "C",
          "dislike_reason": "感情を売買する経済という設定が冷たく感じられ、路面標識や感情相場という表現が商業的すぎて、感情そのものへの敬意が薄れる気がして見たくない。"
        },
        {
          "voter": "Kwesi Liang",
          "like": "B",
          "like_reason": "昔話を語って生きてきた身として、記憶が街中を流れ、誰もが他人の過去を拾えるという発想は語り部の仕事に通じる。水番が歴史を支配するという権力構造も、港の記録係として身近に感じる。",
          "dislike": "A",
          "dislike_reason": "空中の足場や印章による層間管理は面白いが、地に足の着いた人間の営みが見えにくく、倉庫や広場で生きてきた自分にはどこか浮世離れして感じる。"
        },
        {
          "voter": "عمر الحمادي (Omar Al Hammadi)",
          "like": "A",
          "like_reason": "重力の層という物理的・工学的なメカニズムが明確で、電気工学を学ぶ自分にとって世界のルールが論理的に想像しやすい。空中インフラの設計思想に惹かれる。",
          "dislike": "C",
          "dislike_reason": "感情の売買という概念が抽象的すぎて、映像としてどう表現されるのかイメージしにくい。感情相場の数値など経済的比喩が少し過剰に感じる。"
        },
        {
          "voter": "Suphatra Weidmann",
          "like": "B",
          "like_reason": "記憶と権力の構造が鮮明で、水番による情報支配は現実の政治・経営にも通じる。長年マネジメントに携わってきた身として、集合的記憶の操作というテーマに深みを感じる。",
          "dislike": "A",
          "dislike_reason": "重力の層による階層社会は設定として面白いが、視覚的な新鮮さに欠ける気がする。階層社会の描写として既視感があり、もう少し独自性が欲しい。"
        },
        {
          "voter": "たかはし けんと",
          "like": "C",
          "like_reason": "感情が経済として流通するという発想がキャッチーで、ビジネスや相場の概念と組み合わさっていて面白い。社会人として感情労働の比喩としても刺さる。",
          "dislike": "B",
          "dislike_reason": "水路と記憶の世界観は詩的だが、映像的にどう差別化するかが見えにくい。静的なイメージが多く、動きのあるMVとして盛り上がれるか不安。"
        },
        {
          "voter": "Somchai Rattanasak",
          "like": "B",
          "like_reason": "水路が記憶を運ぶという発想は美しく、年を重ねた自分には過去の記憶が消えていく切なさとして共鳴する。干上がった末端水路で生きる貧困層の描写に人間的な重みがある。",
          "dislike": "C",
          "dislike_reason": "炉や感情相場など要素が多すぎて、ストーリーが散漫になりそうな印象。庭仕事や家族との時間を大切にする自分には、記号的・抽象的すぎる世界観が合わない。"
        },
        {
          "voter": "たけし",
          "like": "A",
          "like_reason": "浮遊岩と空中足場という視覚的にわかりやすい世界観で、社会の階層構造も直感的に理解できる。営業職として人と地位の関係を日々意識している身には刺さる設定。",
          "dislike": "B",
          "dislike_reason": "記憶を水路からすくい取るという概念は詩的だが、日常的な感覚からかけ離れすぎていてついていきにくい。石臼型の読み器など道具の説明が多く、世界観の入口が狭い気がする。"
        }
      ],
      "analysis": "[batch 1] Bが3票のlikeを集め、圧倒的な支持を得た。記憶・権力・格差という普遍的テーマが年齢・職業・文化を超えて響いた。Aは少年ペルソナから冒険感で支持を得た一方、生活感との乖離でdislikeも集めた。Cは修理業者から技術的共感を得たが、感情の商品化という冷たさが中高年層に拒否感を生み、dislikeが最多となった。\n[batch 2] AとBが拮抗する展開となった。Aは工学的・構造的明快さと視覚的わかりやすさで工学系の若者や実務経験者から支持を得た。Bは記憶と権力・喪失のテーマが人生経験豊富な中高年層に響き、情緒的な深みで票を集めた。Cは経済・感情という現代的テーマで一部の支持を得たが、設定の複雑さと抽象性が複数のdislikeを引き寄せる結果となった。",
      "is_tiebreak": false,
      "tiebreak_reason": null,
      "goji_vote": null
    }
  },
  "phase4": {
    "proposals": [
      {
        "persona_name": "ミン・チェン",
        "persona_id": "persona-12997349",
        "summary": "企画: 不在の証拠映像——ハーピーが去った後の空間を追いかけることで、視聴者が「何があったか」を逆算する構造\n展開: 無人の水路沿いに揺れる残像。口枷の金具だけが光る暗がり。 → 六本腕が水面を引っ掻く。すくい上げた水がすぐに指の間から零れ落ちる。 → 水路の行燈が赤く明滅し始める。腕の動きが速くなるほど水面の残像が増殖する。 → ハーピーが立ち去った水路に、掻き乱された水面だけが残る。残像が静止する。 → 空の石造り水路に金色の光が充填し、誰も見ていない水面が輝く。\n冒頭: 開始2秒——水路の水面に映る六本腕の影が石畳を這う\n問い: 口枷をはめた腕が水路の底を掻き続けているのに、何も浮かび上がってこない\n場面: 石造り水路の交差点, 発光段差の滝壺広場, 石臼型読み器が並ぶ水辺の縁台, 行燈看板の路地裏, 無人の水路終端の袋小路\nカメラ: 固定ロングショット（序盤）→手持ちの揺れ（中盤）→機械的なスライダー移動（クライマックス）→無人固定ショット（outro）\nカット哲学: hard_cutを基本軸とし、水路の流れに合わせてmatch_cutでsetpiece間を接続。bridge以降はsmash_cutで感情の破断を表現する。",
        "issues": []
      },
      {
        "persona_name": "黄 玉蘭 (Huang Yu-lan)",
        "persona_id": "persona-fafeaa10",
        "summary": "企画: 空間証言ドキュメント——去った存在の痕跡を水路が段階的に析出する過程を追跡する映像\n展開: 干上がりかけた支流の石底に、六本腕の形の湿り跡だけが残っている。水はなく、ハーピーもいない → 水路が少しずつ満ち始め、流れ込んだ水が湿り跡の輪郭に沿って光の筋を作る。形は記憶しているのか → 幹線水路の水面に、ハーピーが立っていた時には見えなかった波紋の記録が次々と浮かび上がる。水路が過去の接触を反芻している → 暗渠の天井面に、口枷の金具が擦れた跡の形で記憶の光が凝固している。ハーピーが通った事実を、空間だけが正確に保存している → 夜明けの水路に、ハーピーの存在が一切ない。しかし水の流れが六本腕の形の渦を繰り返し作り続けている\n冒頭: 石底に刻まれた六本腕の形の湿り跡——水もハーピーもなく、形だけがフレームを占有している最初の3秒\n問い: この六本腕の形の跡が誰のものか——水路はなぜその形を覚えているのか\n場面: 干上がり支流の石底, 光析出の支流分岐, 幹線水路の反芻水面, 行燈路地の感情色分岐点, 暗渠の証言天井\nカメラ: 地面密着超低角→固定俯瞰→手持ちトラッキング→逆光シルエット固定→天井見上げ長回し→完全俯瞰静止\nカット哲学: insert_cutで空間ディテールを証拠として挟み、match_cutで水路形態間を接続。smash_cutはbridge1点のみ使用し衝撃を集中させる",
        "issues": []
      },
      {
        "persona_name": "Henrik Vandenberg",
        "persona_id": "persona-85fe95b7",
        "summary": "企画: 空間証言ドキュメント形式。去った存在の痕跡を、空間が自律的に開示していく過程を追う\n展開: 水路の水面に口枷の金具片が浮かんで流れてくる。誰もいない鍵置き場の壁に、六本分の引っ掻き痕がある → 水路管理室の石臼型読み器が自動で回転を始め、壁面に光の残像が滲み出す。しかし読み器を扱う人物はいない → 干上がった噴水広場の底に六本の腕型の凹みが刻まれており、雨水が溜まるにつれて凹みが光り始める → 鍵置き場の全ての鍵が一斉に揺れ、水路の水が逆流する。壁面の残像が一瞬だけハーピーの輪郭をかたどって消える → 水路管理室の読み器が止まり、水面が静止する。口枷の金具片だけが石臼の縁に引っかかって残る\n冒頭: 水路を流れてくる口枷の金具片が画面中央に引っかかって止まる瞬間\n問い: 口枷は誰が、この水路に流したのか\n場面: 水路管理室, 石造り水路本流, 鍵置き場, 干上がった噴水広場, 水路分岐点の橋下\nカメラ: 固定長回し→低角度追尾→俯瞰降下→ハンドヘルド探索→ラックフォーカス往復→最終固定静止\nカット哲学: match_cut主軸で水路の流れ方向を跨いで空間を接続し、記憶の連続性を形状で繋ぐ",
        "issues": []
      }
    ],
    "vote": {
      "winner_key": "C",
      "tally": {
        "A": 4,
        "B": 8,
        "C": 8
      },
      "like_tally": {
        "A": 3,
        "B": 2,
        "C": 5
      },
      "dislike_tally": {
        "A": 1,
        "B": 6,
        "C": 3
      },
      "votes": [
        {
          "voter": "林美華",
          "like": "C",
          "like_reason": "物が自律的に動き出す演出が視覚的に分かりやすく、謎の入口として引き込まれやすい。口枷の金具片という具体的な「物」が流れる冒頭は日常の延長として受け取りやすい。",
          "dislike": "B",
          "dislike_reason": "湿り跡や波紋の記録など抽象的な痕跡の積み重ねで、何を見せられているのか途中で分からなくなりそう。薬剤師として具体的な因果関係を求める目線には曖昧すぎる。"
        },
        {
          "voter": "陳素華 (Chen Su-hua)",
          "like": "B",
          "like_reason": "水が形を記憶するという詩的な構造に、記録と証拠を扱う仕事柄として強く共鳴する。暗渠の天井に刻まれた痕跡という着想が文学的で格調がある。",
          "dislike": "C",
          "dislike_reason": "鍵が揺れたり水が逆流したりと現象が多すぎて散漫に映る。証言の積み重ねとして見せたいのに、演出の過多が逆に信憑性を削いでいる。"
        },
        {
          "voter": "中村 健太",
          "like": "A",
          "like_reason": "冒頭2秒で影が石畳を這うシーンはインパクトがあって続きを見たくなる。カメラワークの変化（固定→手持ち→スライダー）がテンポを作っていて飽きにくそう。",
          "dislike": "B",
          "dislike_reason": "干上がった石底の湿り跡とか、波紋の記録とか、地味な映像が延々続きそうで眠くなりそう。夜勤明けに見たら確実に寝落ちする。"
        },
        {
          "voter": "Layla al-Mahmoud",
          "like": "A",
          "like_reason": "「不在の証拠」という概念設計が論理的で、在庫管理の仕事と似た発想——何がないかから何があったかを読み取る——に近く自然に没入できる。smash_cutの破断感も好み。",
          "dislike": "C",
          "dislike_reason": "物が勝手に動く演出はホラー的な文脈と混同されやすく、世界観の一貫性が崩れる懸念がある。管理する側の視点として、制御不能な現象の羅列は落ち着かない。"
        },
        {
          "voter": "たけし",
          "like": "C",
          "like_reason": "金具片が流れてきて止まるという冒頭は掴みとして明快。石臼の読み器や鍵置き場など具体的な場所の機能が分かるので世界観への入りが楽。営業職として「掴み」の重要性は理解している。",
          "dislike": "B",
          "dislike_reason": "天井見上げ長回しや完全俯瞰静止など、カメラワークが凝りすぎていて伝えたいことより撮影者のこだわりが前に出すぎている印象。普通の視聴者には置いてけぼり感がある。"
        },
        {
          "voter": "けんと",
          "like": "C",
          "like_reason": "口枷の金具が流れてくる冒頭が直感的でわかりやすく、「誰が流したのか」という問いが素直に気になる。島育ちで水路や水辺の感覚が身近なので映像が頭に浮かびやすい。",
          "dislike": "B",
          "dislike_reason": "「六本腕の形の渦」とか「反芻水面」とか、説明が難解で何を見せられているかわからなくなりそう。仕事終わりに見るには疲れる。"
        },
        {
          "voter": "Rajendra Iyer",
          "like": "B",
          "like_reason": "空間が痕跡を段階的に「析出」するという概念が科学的観察に近く知的興味を引く。記録と証拠という構造が帳簿管理の思考様式と合致し、最後まで追いたくなる。",
          "dislike": "C",
          "dislike_reason": "鍵や読み器が「自動で動く」という超常的演出が唐突で、論理的な因果関係が見えにくい。商人として因果の不明瞭さは居心地が悪い。"
        },
        {
          "voter": "おおた さゆり",
          "like": "A",
          "like_reason": "去った後の空間を追いかけて「何があったか」を逆算するという構造が、静かで切なくて好き。図書館で読む余韻のある小説に近い感覚がある。",
          "dislike": "B",
          "dislike_reason": "「水路が過去の接触を反芻している」など詩的すぎて、映像として何が映るのか想像できない。難しくて疲れそう。"
        },
        {
          "voter": "Kwesi Liang",
          "like": "C",
          "like_reason": "物が自然に動いて話が展開していく様子が、広場で語る昔話の流れに似ていて馴染みやすい。口枷が流れてきて引っかかるという冒頭は人を引き込む語り口だ。",
          "dislike": "A",
          "dislike_reason": "最初から最後まで誰もいない映像ばかりでは、話し相手がいない酒場のようで寂しい。残像だけでは物語を語る相手がいない感じがして退屈しそうだ。"
        },
        {
          "voter": "ゆうと",
          "like": "C",
          "like_reason": "鍵が揺れたり水が逆流したりと動きのある演出が多くて飽きない。コンビニ弁当食べながらでも追いやすいテンポで、一番最後まで見られそう。",
          "dislike": "B",
          "dislike_reason": "カメラアングルの説明が多すぎて、映像を見る前から難しそうな印象。地面密着超低角とか天井見上げ長回しとか、ただただ酔いそう。"
        },
        {
          "voter": "ゴジ",
          "like": "B",
          "like_reason": "「水が形を記憶している」という問いが一貫していて、六本腕の渦という具体的な映像に落ちている。抽象に逃げずに水という物質で答えを出そうとしている点が誠実",
          "dislike": "C",
          "dislike_reason": "口枷の金具片・石臼型読み器・鍵置き場と小道具が多すぎて、「誰が流したのか」という問いが散漫になる。Bと同じ空間証言形式でありながら焦点が定まらず、見ていて何を追えばいいか分からなくなりそう"
        }
      ],
      "analysis": "[batch 1] AとCが各2票のlikeを獲得し拮抗している。Aは「不在から逆算する」という構造の明快さとカメラワークの変化が評価された一方、Cは冒頭の具体的な「物の動き」による掴みの分かりやすさが支持された。Bは詩的・文学的な評価を受けたペルソナには刺さったが、抽象度の高さと演出の地味さが原因で過半数からdislikeを受ける結果となった。\n[batch 2] CとBが票を分け合う構図となった。Cは冒頭の具体的なフックと動きのある演出で幅広い層に支持されたが、Bは知的・分析的な視聴者には響く一方で難解さゆえに最多dislikeを集めた。Aは静的・余韻重視の設計が刺さる層には強く支持されたが、エンターテインメント性を求める層からは敬遠された。全体的に「空間が記憶を持つ」という共通テーマの中で、視聴者が取っ掛かりを掴めるかどうかが評価を左右している。",
      "is_tiebreak": true,
      "tiebreak_reason": null,
      "goji_vote": {
        "voter": "ゴジ",
        "like": "B",
        "like_reason": "「水が形を記憶している」という問いが一貫していて、六本腕の渦という具体的な映像に落ちている。抽象に逃げずに水という物質で答えを出そうとしている点が誠実",
        "dislike": "C",
        "dislike_reason": "口枷の金具片・石臼型読み器・鍵置き場と小道具が多すぎて、「誰が流したのか」という問いが散漫になる。Bと同じ空間証言形式でありながら焦点が定まらず、見ていて何を追えばいいか分からなくなりそう"
      }
    }
  }
}